Workbook

Sheet Instructions
A1: How to Use: Business Income Tracker 2026
A3: Getting Started
A5: 1. Each monthly tab tracks income received from clients/customers.
A6: 2. Enter the date, client name, product/service, invoice number, amount, payment method, and status.
A7: 3. Use the Status dropdown to mark payments as Paid, Pending, or Overdue.
A8: 4. Monthly totals auto-calculate at the bottom of each tab.
A9: 5. The Dashboard tab shows your annual income summary and YTD running totals.
A10: 6. Filter or sort columns to quickly find specific entries.
A11: 7. Update the Status column regularly to keep cash flow visibility.
A13: Tips & Notes
A14: - Use the dropdown menus for consistent data entry.
A15: - Do not delete or move formula cells - they auto-calculate totals.
... A18: - Customize categories and columns to fit your specific business needs.

Sheet Dashboard
A1: Annual Income Dashboard - 2026
A3: Month | B3: Total Income | C3: Paid | D3: Pending | E3: Overdue | F3: YTD Running Total
A4: January | B4: ='January'!E40 | C4: ='January'!E41 | D4: ='January'!E42 | E4: ='January'!E43 | F4: =B4
A5: February | B5: ='February'!E40 | C5: ='February'!E41 | D5: ='February'!E42 | E5: ='February'!E43 | F5: =F4+B5
A6: March | B6: ='March'!E40 | C6: ='March'!E41 | D6: ='March'!E42 | E6: ='March'!E43 | F6: =F5+B6
A7: April | B7: ='April'!E40 | C7: ='April'!E41 | D7: ='April'!E42 | E7: ='April'!E43 | F7: =F6+B7
A8: May | B8: ='May'!E40 | C8: ='May'!E41 | D8: ='May'!E42 | E8: ='May'!E43 | F8: =F7+B8
A9: June | B9: ='June'!E40 | C9: ='June'!E41 | D9: ='June'!E42 | E9: ='June'!E43 | F9: =F8+B9
A10: July | B10: ='July'!E40 | C10: ='July'!E41 | D10: ='July'!E42 | E10: ='July'!E43 | F10: =F9+B10
A11: August | B11: ='August'!E40 | C11: ='August'!E41 | D11: ='August'!E42 | E11: ='August'!E43 | F11: =F10+B11
A12: September | B12: ='September'!E40 | C12: ='September'!E41 | D12: ='September'!E42 | E12: ='September'!E43 | F12: =F11+B12
A13: October | B13: ='October'!E40 | C13: ='October'!E41 | D13: ='October'!E42 | E13: ='October'!E43 | F13: =F12+B13
A14: November | B14: ='November'!E40 | C14: ='November'!E41 | D14: ='November'!E42 | E14: ='November'!E43 | F14: =F13+B14
A15: December | B15: ='December'!E40 | C15: ='December'!E41 | D15: ='December'!E42 | E15: ='December'!E43 | F15: =F14+B15
A17: ANNUAL TOTAL | B17: =SUM(B4:B15) | C17: =SUM(C4:C15) | D17: =SUM(D4:D15) | E17: =SUM(E4:E15) | F17: =F15

Sheet January
A1: Income Tracker - January 2026
A3: Date | B3: Client/Customer | C3: Product/Service | D3: Invoice # | E3: Amount | F3: Payment Method | G3: Status
D40: Monthly Total: | E40: =SUM(E4:E38)
D41: Total Paid: | E41: =SUMIF(G4:G38,"Paid",E4:E38)
D42: Total Pending: | E42: =SUMIF(G4:G38,"Pending",E4:E38)
D43: Total Overdue: | E43: =SUMIF(G4:G38,"Overdue",E4:E38)

Sheet February
A1: Income Tracker - February 2026
A3: Date | B3: Client/Customer | C3: Product/Service | D3: Invoice # | E3: Amount | F3: Payment Method | G3: Status
D40: Monthly Total: | E40: =SUM(E4:E38)
D41: Total Paid: | E41: =SUMIF(G4:G38,"Paid",E4:E38)
D42: Total Pending: | E42: =SUMIF(G4:G38,"Pending",E4:E38)
D43: Total Overdue: | E43: =SUMIF(G4:G38,"Overdue",E4:E38)

Sheet March
A1: Income Tracker - March 2026
A3: Date | B3: Client/Customer | C3: Product/Service | D3: Invoice # | E3: Amount | F3: Payment Method | G3: Status
D40: Monthly Total: | E40: =SUM(E4:E38)
D41: Total Paid: | E41: =SUMIF(G4:G38,"Paid",E4:E38)
D42: Total Pending: | E42: =SUMIF(G4:G38,"Pending",E4:E38)
D43: Total Overdue: | E43: =SUMIF(G4:G38,"Overdue",E4:E38)

Sheet April
A1: Income Tracker - April 2026
A3: Date | B3: Client/Customer | C3: Product/Service | D3: Invoice # | E3: Amount | F3: Payment Method | G3: Status
D40: Monthly Total: | E40: =SUM(E4:E38)
D41: Total Paid: | E41: =SUMIF(G4:G38,"Paid",E4:E38)
D42: Total Pending: | E42: =SUMIF(G4:G38,"Pending",E4:E38)
D43: Total Overdue: | E43: =SUMIF(G4:G38,"Overdue",E4:E38)

Sheet May
A1: Income Tracker - May 2026
A3: Date | B3: Client/Customer | C3: Product/Service | D3: Invoice # | E3: Amount | F3: Payment Method | G3: Status
D40: Monthly Total: | E40: =SUM(E4:E38)
D41: Total Paid: | E41: =SUMIF(G4:G38,"Paid",E4:E38)
D42: Total Pending: | E42: =SUMIF(G4:G38,"Pending",E4:E38)
D43: Total Overdue: | E43: =SUMIF(G4:G38,"Overdue",E4:E38)

Sheet June
A1: Income Tracker - June 2026
A3: Date | B3: Client/Customer | C3: Product/Service | D3: Invoice # | E3: Amount | F3: Payment Method | G3: Status
D40: Monthly Total: | E40: =SUM(E4:E38)
D41: Total Paid: | E41: =SUMIF(G4:G38,"Paid",E4:E38)
D42: Total Pending: | E42: =SUMIF(G4:G38,"Pending",E4:E38)
D43: Total Overdue: | E43: =SUMIF(G4:G38,"Overdue",E4:E38)

Sheet July
A1: Income Tracker - July 2026
A3: Date | B3: Client/Customer | C3: Product/Service | D3: Invoice # | E3: Amount | F3: Payment Method | G3: Status
D40: Monthly Total: | E40: =SUM(E4:E38)
D41: Total Paid: | E41: =SUMIF(G4:G38,"Paid",E4:E38)
D42: Total Pending: | E42: =SUMIF(G4:G38,"Pending",E4:E38)
D43: Total Overdue: | E43: =SUMIF(G4:G38,"Overdue",E4:E38)

Sheet August
A1: Income Tracker - August 2026
A3: Date | B3: Client/Customer | C3: Product/Service | D3: Invoice # | E3: Amount | F3: Payment Method | G3: Status
D40: Monthly Total: | E40: =SUM(E4:E38)
D41: Total Paid: | E41: =SUMIF(G4:G38,"Paid",E4:E38)
D42: Total Pending: | E42: =SUMIF(G4:G38,"Pending",E4:E38)
D43: Total Overdue: | E43: =SUMIF(G4:G38,"Overdue",E4:E38)

Sheet September
A1: Income Tracker - September 2026
A3: Date | B3: Client/Customer | C3: Product/Service | D3: Invoice # | E3: Amount | F3: Payment Method | G3: Status
D40: Monthly Total: | E40: =SUM(E4:E38)
D41: Total Paid: | E41: =SUMIF(G4:G38,"Paid",E4:E38)
D42: Total Pending: | E42: =SUMIF(G4:G38,"Pending",E4:E38)
D43: Total Overdue: | E43: =SUMIF(G4:G38,"Overdue",E4:E38)

Sheet October
A1: Income Tracker - October 2026
A3: Date | B3: Client/Customer | C3: Product/Service | D3: Invoice # | E3: Amount | F3: Payment Method | G3: Status
D40: Monthly Total: | E40: =SUM(E4:E38)
D41: Total Paid: | E41: =SUMIF(G4:G38,"Paid",E4:E38)
D42: Total Pending: | E42: =SUMIF(G4:G38,"Pending",E4:E38)
D43: Total Overdue: | E43: =SUMIF(G4:G38,"Overdue",E4:E38)

Sheet November
A1: Income Tracker - November 2026
A3: Date | B3: Client/Customer | C3: Product/Service | D3: Invoice # | E3: Amount | F3: Payment Method | G3: Status
D40: Monthly Total: | E40: =SUM(E4:E38)
D41: Total Paid: | E41: =SUMIF(G4:G38,"Paid",E4:E38)
D42: Total Pending: | E42: =SUMIF(G4:G38,"Pending",E4:E38)
D43: Total Overdue: | E43: =SUMIF(G4:G38,"Overdue",E4:E38)

Sheet December
A1: Income Tracker - December 2026
A3: Date | B3: Client/Customer | C3: Product/Service | D3: Invoice # | E3: Amount | F3: Payment Method | G3: Status
D40: Monthly Total: | E40: =SUM(E4:E38)
D41: Total Paid: | E41: =SUMIF(G4:G38,"Paid",E4:E38)
D42: Total Pending: | E42: =SUMIF(G4:G38,"Pending",E4:E38)
D43: Total Overdue: | E43: =SUMIF(G4:G38,"Overdue",E4:E38)
