Workbook

Sheet Instructions
A1: How to Use: Profit & Loss Statement 2026
A3: Getting Started
A5: 1. Enter your Revenue, Cost of Goods Sold (COGS), and Operating Expenses each month.
A6: 2. Gross Profit, Operating Income, and Net Profit are auto-calculated.
A7: 3. Margins and percentages update automatically based on your entries.
A8: 4. The 12-Month Comparison view shows trends across the full year.
A9: 5. Use this to understand your profitability month over month.
A10: 6. Compare categories to identify areas for cost reduction.
A11: 7. Share with your accountant for tax preparation.
A13: Tips & Notes
A14: - Use the dropdown menus for consistent data entry.
A15: - Do not delete or move formula cells - they auto-calculate totals.
... A18: - Customize categories and columns to fit your specific business needs.

Sheet 12-Month Comparison
A1: 12-Month Profit & Loss Comparison - 2026
A3: Category | B3: January | C3: February | D3: March | E3: April | F3: May | G3: June | H3: July | I3: August | J3: September | K3: October | L3: November | M3: December | N3: Annual Total
A4: Total Revenue | B4: ='January'!B7 | C4: ='February'!B7 | D4: ='March'!B7 | E4: ='April'!B7 | F4: ='May'!B7 | G4: ='June'!B7 | H4: ='July'!B7 | I4: ='August'!B7 | J4: ='September'!B7 | K4: ='October'!B7 | L4: ='November'!B7 | M4: ='December'!B7 | N4: =SUM(B4:M4)
A5: Total COGS | B5: ='January'!B12 | C5: ='February'!B12 | D5: ='March'!B12 | E5: ='April'!B12 | F5: ='May'!B12 | G5: ='June'!B12 | H5: ='July'!B12 | I5: ='August'!B12 | J5: ='September'!B12 | K5: ='October'!B12 | L5: ='November'!B12 | M5: ='December'!B12 | N5: =SUM(B5:M5)
A6: Gross Profit | B6: ='January'!B13 | C6: ='February'!B13 | D6: ='March'!B13 | E6: ='April'!B13 | F6: ='May'!B13 | G6: ='June'!B13 | H6: ='July'!B13 | I6: ='August'!B13 | J6: ='September'!B13 | K6: ='October'!B13 | L6: ='November'!B13 | M6: ='December'!B13 | N6: =SUM(B6:M6)
A7: Total Operating Expenses | B7: ='January'!B28 | C7: ='February'!B28 | D7: ='March'!B28 | E7: ='April'!B28 | F7: ='May'!B28 | G7: ='June'!B28 | H7: ='July'!B28 | I7: ='August'!B28 | J7: ='September'!B28 | K7: ='October'!B28 | L7: ='November'!B28 | M7: ='December'!B28 | N7: =SUM(B7:M7)
A8: Net Profit / (Loss) | B8: ='January'!B30 | C8: ='February'!B30 | D8: ='March'!B30 | E8: ='April'!B30 | F8: ='May'!B30 | G8: ='June'!B30 | H8: ='July'!B30 | I8: ='August'!B30 | J8: ='September'!B30 | K8: ='October'!B30 | L8: ='November'!B30 | M8: ='December'!B30 | N8: =SUM(B8:M8)

Sheet January
A1: Profit & Loss Statement - January 2026
A3: REVENUE | B3: Amount | C3: % of Revenue
A4: Product Sales | C4: =IF(B7=0,0,B4/B7)
A5: Service Revenue | C5: =IF(B7=0,0,B5/B7)
A6: Other Revenue | C6: =IF(B7=0,0,B6/B7)
A7: Total Revenue | B7: =SUM(B4:B6) | C7: 1
A9: COST OF GOODS SOLD
A10: Materials & Supplies | C10: =IF(B7=0,0,B10/B7)
A11: Direct Labor | C11: =IF(B7=0,0,B11/B7)
A12: Shipping & Fulfillment | C12: =IF(B7=0,0,B12/B7)
A13: Total COGS | B13: =SUM(B10:B12) | C13: =IF(B7=0,0,B13/B7)
A14: GROSS PROFIT | B14: =B7-B13 | C14: =IF(B7=0,0,B14/B7)
A16: OPERATING EXPENSES
A17: Supplies & Materials | C17: =IF(B7=0,0,B17/B7)
A18: Marketing & Advertising | C18: =IF(B7=0,0,B18/B7)
A19: Software & Subscriptions | C19: =IF(B7=0,0,B19/B7)
A20: Travel & Transportation | C20: =IF(B7=0,0,B20/B7)
A21: Meals & Entertainment | C21: =IF(B7=0,0,B21/B7)
A22: Office Expenses | C22: =IF(B7=0,0,B22/B7)
A23: Professional Services | C23: =IF(B7=0,0,B23/B7)
A24: Insurance | C24: =IF(B7=0,0,B24/B7)
A25: Utilities & Rent | C25: =IF(B7=0,0,B25/B7)
A26: Payroll & Contractors | C26: =IF(B7=0,0,B26/B7)
A27: Depreciation | C27: =IF(B7=0,0,B27/B7)
A28: Other Expenses | C28: =IF(B7=0,0,B28/B7)
A29: Total Operating Expenses | B29: =SUM(B17:B28) | C29: =IF(B7=0,0,B29/B7)
A31: NET PROFIT / (LOSS) | B31: =B14-B29 | C31: =IF(B7=0,0,B31/B7)

Sheet February
A1: Profit & Loss Statement - February 2026
A3: REVENUE | B3: Amount | C3: % of Revenue
A4: Product Sales | C4: =IF(B7=0,0,B4/B7)
A5: Service Revenue | C5: =IF(B7=0,0,B5/B7)
A6: Other Revenue | C6: =IF(B7=0,0,B6/B7)
A7: Total Revenue | B7: =SUM(B4:B6) | C7: 1
A9: COST OF GOODS SOLD
A10: Materials & Supplies | C10: =IF(B7=0,0,B10/B7)
A11: Direct Labor | C11: =IF(B7=0,0,B11/B7)
A12: Shipping & Fulfillment | C12: =IF(B7=0,0,B12/B7)
A13: Total COGS | B13: =SUM(B10:B12) | C13: =IF(B7=0,0,B13/B7)
A14: GROSS PROFIT | B14: =B7-B13 | C14: =IF(B7=0,0,B14/B7)
A16: OPERATING EXPENSES
A17: Supplies & Materials | C17: =IF(B7=0,0,B17/B7)
A18: Marketing & Advertising | C18: =IF(B7=0,0,B18/B7)
A19: Software & Subscriptions | C19: =IF(B7=0,0,B19/B7)
A20: Travel & Transportation | C20: =IF(B7=0,0,B20/B7)
A21: Meals & Entertainment | C21: =IF(B7=0,0,B21/B7)
A22: Office Expenses | C22: =IF(B7=0,0,B22/B7)
A23: Professional Services | C23: =IF(B7=0,0,B23/B7)
A24: Insurance | C24: =IF(B7=0,0,B24/B7)
A25: Utilities & Rent | C25: =IF(B7=0,0,B25/B7)
A26: Payroll & Contractors | C26: =IF(B7=0,0,B26/B7)
A27: Depreciation | C27: =IF(B7=0,0,B27/B7)
A28: Other Expenses | C28: =IF(B7=0,0,B28/B7)
A29: Total Operating Expenses | B29: =SUM(B17:B28) | C29: =IF(B7=0,0,B29/B7)
A31: NET PROFIT / (LOSS) | B31: =B14-B29 | C31: =IF(B7=0,0,B31/B7)

Sheet March
A1: Profit & Loss Statement - March 2026
A3: REVENUE | B3: Amount | C3: % of Revenue
A4: Product Sales | C4: =IF(B7=0,0,B4/B7)
A5: Service Revenue | C5: =IF(B7=0,0,B5/B7)
A6: Other Revenue | C6: =IF(B7=0,0,B6/B7)
A7: Total Revenue | B7: =SUM(B4:B6) | C7: 1
A9: COST OF GOODS SOLD
A10: Materials & Supplies | C10: =IF(B7=0,0,B10/B7)
A11: Direct Labor | C11: =IF(B7=0,0,B11/B7)
A12: Shipping & Fulfillment | C12: =IF(B7=0,0,B12/B7)
A13: Total COGS | B13: =SUM(B10:B12) | C13: =IF(B7=0,0,B13/B7)
A14: GROSS PROFIT | B14: =B7-B13 | C14: =IF(B7=0,0,B14/B7)
A16: OPERATING EXPENSES
A17: Supplies & Materials | C17: =IF(B7=0,0,B17/B7)
A18: Marketing & Advertising | C18: =IF(B7=0,0,B18/B7)
A19: Software & Subscriptions | C19: =IF(B7=0,0,B19/B7)
A20: Travel & Transportation | C20: =IF(B7=0,0,B20/B7)
A21: Meals & Entertainment | C21: =IF(B7=0,0,B21/B7)
A22: Office Expenses | C22: =IF(B7=0,0,B22/B7)
A23: Professional Services | C23: =IF(B7=0,0,B23/B7)
A24: Insurance | C24: =IF(B7=0,0,B24/B7)
A25: Utilities & Rent | C25: =IF(B7=0,0,B25/B7)
A26: Payroll & Contractors | C26: =IF(B7=0,0,B26/B7)
A27: Depreciation | C27: =IF(B7=0,0,B27/B7)
A28: Other Expenses | C28: =IF(B7=0,0,B28/B7)
A29: Total Operating Expenses | B29: =SUM(B17:B28) | C29: =IF(B7=0,0,B29/B7)
A31: NET PROFIT / (LOSS) | B31: =B14-B29 | C31: =IF(B7=0,0,B31/B7)

Sheet April
A1: Profit & Loss Statement - April 2026
A3: REVENUE | B3: Amount | C3: % of Revenue
A4: Product Sales | C4: =IF(B7=0,0,B4/B7)
A5: Service Revenue | C5: =IF(B7=0,0,B5/B7)
A6: Other Revenue | C6: =IF(B7=0,0,B6/B7)
A7: Total Revenue | B7: =SUM(B4:B6) | C7: 1
A9: COST OF GOODS SOLD
A10: Materials & Supplies | C10: =IF(B7=0,0,B10/B7)
A11: Direct Labor | C11: =IF(B7=0,0,B11/B7)
A12: Shipping & Fulfillment | C12: =IF(B7=0,0,B12/B7)
A13: Total COGS | B13: =SUM(B10:B12) | C13: =IF(B7=0,0,B13/B7)
A14: GROSS PROFIT | B14: =B7-B13 | C14: =IF(B7=0,0,B14/B7)
A16: OPERATING EXPENSES
A17: Supplies & Materials | C17: =IF(B7=0,0,B17/B7)
A18: Marketing & Advertising | C18: =IF(B7=0,0,B18/B7)
A19: Software & Subscriptions | C19: =IF(B7=0,0,B19/B7)
A20: Travel & Transportation | C20: =IF(B7=0,0,B20/B7)
A21: Meals & Entertainment | C21: =IF(B7=0,0,B21/B7)
A22: Office Expenses | C22: =IF(B7=0,0,B22/B7)
A23: Professional Services | C23: =IF(B7=0,0,B23/B7)
A24: Insurance | C24: =IF(B7=0,0,B24/B7)
A25: Utilities & Rent | C25: =IF(B7=0,0,B25/B7)
A26: Payroll & Contractors | C26: =IF(B7=0,0,B26/B7)
A27: Depreciation | C27: =IF(B7=0,0,B27/B7)
A28: Other Expenses | C28: =IF(B7=0,0,B28/B7)
A29: Total Operating Expenses | B29: =SUM(B17:B28) | C29: =IF(B7=0,0,B29/B7)
A31: NET PROFIT / (LOSS) | B31: =B14-B29 | C31: =IF(B7=0,0,B31/B7)

Sheet May
A1: Profit & Loss Statement - May 2026
A3: REVENUE | B3: Amount | C3: % of Revenue
A4: Product Sales | C4: =IF(B7=0,0,B4/B7)
A5: Service Revenue | C5: =IF(B7=0,0,B5/B7)
A6: Other Revenue | C6: =IF(B7=0,0,B6/B7)
A7: Total Revenue | B7: =SUM(B4:B6) | C7: 1
A9: COST OF GOODS SOLD
A10: Materials & Supplies | C10: =IF(B7=0,0,B10/B7)
A11: Direct Labor | C11: =IF(B7=0,0,B11/B7)
A12: Shipping & Fulfillment | C12: =IF(B7=0,0,B12/B7)
A13: Total COGS | B13: =SUM(B10:B12) | C13: =IF(B7=0,0,B13/B7)
A14: GROSS PROFIT | B14: =B7-B13 | C14: =IF(B7=0,0,B14/B7)
A16: OPERATING EXPENSES
A17: Supplies & Materials | C17: =IF(B7=0,0,B17/B7)
A18: Marketing & Advertising | C18: =IF(B7=0,0,B18/B7)
A19: Software & Subscriptions | C19: =IF(B7=0,0,B19/B7)
A20: Travel & Transportation | C20: =IF(B7=0,0,B20/B7)
A21: Meals & Entertainment | C21: =IF(B7=0,0,B21/B7)
A22: Office Expenses | C22: =IF(B7=0,0,B22/B7)
A23: Professional Services | C23: =IF(B7=0,0,B23/B7)
A24: Insurance | C24: =IF(B7=0,0,B24/B7)
A25: Utilities & Rent | C25: =IF(B7=0,0,B25/B7)
A26: Payroll & Contractors | C26: =IF(B7=0,0,B26/B7)
A27: Depreciation | C27: =IF(B7=0,0,B27/B7)
A28: Other Expenses | C28: =IF(B7=0,0,B28/B7)
A29: Total Operating Expenses | B29: =SUM(B17:B28) | C29: =IF(B7=0,0,B29/B7)
A31: NET PROFIT / (LOSS) | B31: =B14-B29 | C31: =IF(B7=0,0,B31/B7)

Sheet June
A1: Profit & Loss Statement - June 2026
A3: REVENUE | B3: Amount | C3: % of Revenue
A4: Product Sales | C4: =IF(B7=0,0,B4/B7)
A5: Service Revenue | C5: =IF(B7=0,0,B5/B7)
A6: Other Revenue | C6: =IF(B7=0,0,B6/B7)
A7: Total Revenue | B7: =SUM(B4:B6) | C7: 1
A9: COST OF GOODS SOLD
A10: Materials & Supplies | C10: =IF(B7=0,0,B10/B7)
A11: Direct Labor | C11: =IF(B7=0,0,B11/B7)
A12: Shipping & Fulfillment | C12: =IF(B7=0,0,B12/B7)
A13: Total COGS | B13: =SUM(B10:B12) | C13: =IF(B7=0,0,B13/B7)
A14: GROSS PROFIT | B14: =B7-B13 | C14: =IF(B7=0,0,B14/B7)
A16: OPERATING EXPENSES
A17: Supplies & Materials | C17: =IF(B7=0,0,B17/B7)
A18: Marketing & Advertising | C18: =IF(B7=0,0,B18/B7)
A19: Software & Subscriptions | C19: =IF(B7=0,0,B19/B7)
A20: Travel & Transportation | C20: =IF(B7=0,0,B20/B7)
A21: Meals & Entertainment | C21: =IF(B7=0,0,B21/B7)
A22: Office Expenses | C22: =IF(B7=0,0,B22/B7)
A23: Professional Services | C23: =IF(B7=0,0,B23/B7)
A24: Insurance | C24: =IF(B7=0,0,B24/B7)
A25: Utilities & Rent | C25: =IF(B7=0,0,B25/B7)
A26: Payroll & Contractors | C26: =IF(B7=0,0,B26/B7)
A27: Depreciation | C27: =IF(B7=0,0,B27/B7)
A28: Other Expenses | C28: =IF(B7=0,0,B28/B7)
A29: Total Operating Expenses | B29: =SUM(B17:B28) | C29: =IF(B7=0,0,B29/B7)
A31: NET PROFIT / (LOSS) | B31: =B14-B29 | C31: =IF(B7=0,0,B31/B7)

Sheet July
A1: Profit & Loss Statement - July 2026
A3: REVENUE | B3: Amount | C3: % of Revenue
A4: Product Sales | C4: =IF(B7=0,0,B4/B7)
A5: Service Revenue | C5: =IF(B7=0,0,B5/B7)
A6: Other Revenue | C6: =IF(B7=0,0,B6/B7)
A7: Total Revenue | B7: =SUM(B4:B6) | C7: 1
A9: COST OF GOODS SOLD
A10: Materials & Supplies | C10: =IF(B7=0,0,B10/B7)
A11: Direct Labor | C11: =IF(B7=0,0,B11/B7)
A12: Shipping & Fulfillment | C12: =IF(B7=0,0,B12/B7)
A13: Total COGS | B13: =SUM(B10:B12) | C13: =IF(B7=0,0,B13/B7)
A14: GROSS PROFIT | B14: =B7-B13 | C14: =IF(B7=0,0,B14/B7)
A16: OPERATING EXPENSES
A17: Supplies & Materials | C17: =IF(B7=0,0,B17/B7)
A18: Marketing & Advertising | C18: =IF(B7=0,0,B18/B7)
A19: Software & Subscriptions | C19: =IF(B7=0,0,B19/B7)
A20: Travel & Transportation | C20: =IF(B7=0,0,B20/B7)
A21: Meals & Entertainment | C21: =IF(B7=0,0,B21/B7)
A22: Office Expenses | C22: =IF(B7=0,0,B22/B7)
A23: Professional Services | C23: =IF(B7=0,0,B23/B7)
A24: Insurance | C24: =IF(B7=0,0,B24/B7)
A25: Utilities & Rent | C25: =IF(B7=0,0,B25/B7)
A26: Payroll & Contractors | C26: =IF(B7=0,0,B26/B7)
A27: Depreciation | C27: =IF(B7=0,0,B27/B7)
A28: Other Expenses | C28: =IF(B7=0,0,B28/B7)
A29: Total Operating Expenses | B29: =SUM(B17:B28) | C29: =IF(B7=0,0,B29/B7)
A31: NET PROFIT / (LOSS) | B31: =B14-B29 | C31: =IF(B7=0,0,B31/B7)

Sheet August
A1: Profit & Loss Statement - August 2026
A3: REVENUE | B3: Amount | C3: % of Revenue
A4: Product Sales | C4: =IF(B7=0,0,B4/B7)
A5: Service Revenue | C5: =IF(B7=0,0,B5/B7)
A6: Other Revenue | C6: =IF(B7=0,0,B6/B7)
A7: Total Revenue | B7: =SUM(B4:B6) | C7: 1
A9: COST OF GOODS SOLD
A10: Materials & Supplies | C10: =IF(B7=0,0,B10/B7)
A11: Direct Labor | C11: =IF(B7=0,0,B11/B7)
A12: Shipping & Fulfillment | C12: =IF(B7=0,0,B12/B7)
A13: Total COGS | B13: =SUM(B10:B12) | C13: =IF(B7=0,0,B13/B7)
A14: GROSS PROFIT | B14: =B7-B13 | C14: =IF(B7=0,0,B14/B7)
A16: OPERATING EXPENSES
A17: Supplies & Materials | C17: =IF(B7=0,0,B17/B7)
A18: Marketing & Advertising | C18: =IF(B7=0,0,B18/B7)
A19: Software & Subscriptions | C19: =IF(B7=0,0,B19/B7)
A20: Travel & Transportation | C20: =IF(B7=0,0,B20/B7)
A21: Meals & Entertainment | C21: =IF(B7=0,0,B21/B7)
A22: Office Expenses | C22: =IF(B7=0,0,B22/B7)
A23: Professional Services | C23: =IF(B7=0,0,B23/B7)
A24: Insurance | C24: =IF(B7=0,0,B24/B7)
A25: Utilities & Rent | C25: =IF(B7=0,0,B25/B7)
A26: Payroll & Contractors | C26: =IF(B7=0,0,B26/B7)
A27: Depreciation | C27: =IF(B7=0,0,B27/B7)
A28: Other Expenses | C28: =IF(B7=0,0,B28/B7)
A29: Total Operating Expenses | B29: =SUM(B17:B28) | C29: =IF(B7=0,0,B29/B7)
A31: NET PROFIT / (LOSS) | B31: =B14-B29 | C31: =IF(B7=0,0,B31/B7)

Sheet September
A1: Profit & Loss Statement - September 2026
A3: REVENUE | B3: Amount | C3: % of Revenue
A4: Product Sales | C4: =IF(B7=0,0,B4/B7)
A5: Service Revenue | C5: =IF(B7=0,0,B5/B7)
A6: Other Revenue | C6: =IF(B7=0,0,B6/B7)
A7: Total Revenue | B7: =SUM(B4:B6) | C7: 1
A9: COST OF GOODS SOLD
A10: Materials & Supplies | C10: =IF(B7=0,0,B10/B7)
A11: Direct Labor | C11: =IF(B7=0,0,B11/B7)
A12: Shipping & Fulfillment | C12: =IF(B7=0,0,B12/B7)
A13: Total COGS | B13: =SUM(B10:B12) | C13: =IF(B7=0,0,B13/B7)
A14: GROSS PROFIT | B14: =B7-B13 | C14: =IF(B7=0,0,B14/B7)
A16: OPERATING EXPENSES
A17: Supplies & Materials | C17: =IF(B7=0,0,B17/B7)
A18: Marketing & Advertising | C18: =IF(B7=0,0,B18/B7)
A19: Software & Subscriptions | C19: =IF(B7=0,0,B19/B7)
A20: Travel & Transportation | C20: =IF(B7=0,0,B20/B7)
A21: Meals & Entertainment | C21: =IF(B7=0,0,B21/B7)
A22: Office Expenses | C22: =IF(B7=0,0,B22/B7)
A23: Professional Services | C23: =IF(B7=0,0,B23/B7)
A24: Insurance | C24: =IF(B7=0,0,B24/B7)
A25: Utilities & Rent | C25: =IF(B7=0,0,B25/B7)
A26: Payroll & Contractors | C26: =IF(B7=0,0,B26/B7)
A27: Depreciation | C27: =IF(B7=0,0,B27/B7)
A28: Other Expenses | C28: =IF(B7=0,0,B28/B7)
A29: Total Operating Expenses | B29: =SUM(B17:B28) | C29: =IF(B7=0,0,B29/B7)
A31: NET PROFIT / (LOSS) | B31: =B14-B29 | C31: =IF(B7=0,0,B31/B7)

Sheet October
A1: Profit & Loss Statement - October 2026
A3: REVENUE | B3: Amount | C3: % of Revenue
A4: Product Sales | C4: =IF(B7=0,0,B4/B7)
A5: Service Revenue | C5: =IF(B7=0,0,B5/B7)
A6: Other Revenue | C6: =IF(B7=0,0,B6/B7)
A7: Total Revenue | B7: =SUM(B4:B6) | C7: 1
A9: COST OF GOODS SOLD
A10: Materials & Supplies | C10: =IF(B7=0,0,B10/B7)
A11: Direct Labor | C11: =IF(B7=0,0,B11/B7)
A12: Shipping & Fulfillment | C12: =IF(B7=0,0,B12/B7)
A13: Total COGS | B13: =SUM(B10:B12) | C13: =IF(B7=0,0,B13/B7)
A14: GROSS PROFIT | B14: =B7-B13 | C14: =IF(B7=0,0,B14/B7)
A16: OPERATING EXPENSES
A17: Supplies & Materials | C17: =IF(B7=0,0,B17/B7)
A18: Marketing & Advertising | C18: =IF(B7=0,0,B18/B7)
A19: Software & Subscriptions | C19: =IF(B7=0,0,B19/B7)
A20: Travel & Transportation | C20: =IF(B7=0,0,B20/B7)
A21: Meals & Entertainment | C21: =IF(B7=0,0,B21/B7)
A22: Office Expenses | C22: =IF(B7=0,0,B22/B7)
A23: Professional Services | C23: =IF(B7=0,0,B23/B7)
A24: Insurance | C24: =IF(B7=0,0,B24/B7)
A25: Utilities & Rent | C25: =IF(B7=0,0,B25/B7)
A26: Payroll & Contractors | C26: =IF(B7=0,0,B26/B7)
A27: Depreciation | C27: =IF(B7=0,0,B27/B7)
A28: Other Expenses | C28: =IF(B7=0,0,B28/B7)
A29: Total Operating Expenses | B29: =SUM(B17:B28) | C29: =IF(B7=0,0,B29/B7)
A31: NET PROFIT / (LOSS) | B31: =B14-B29 | C31: =IF(B7=0,0,B31/B7)

Sheet November
A1: Profit & Loss Statement - November 2026
A3: REVENUE | B3: Amount | C3: % of Revenue
A4: Product Sales | C4: =IF(B7=0,0,B4/B7)
A5: Service Revenue | C5: =IF(B7=0,0,B5/B7)
A6: Other Revenue | C6: =IF(B7=0,0,B6/B7)
A7: Total Revenue | B7: =SUM(B4:B6) | C7: 1
A9: COST OF GOODS SOLD
A10: Materials & Supplies | C10: =IF(B7=0,0,B10/B7)
A11: Direct Labor | C11: =IF(B7=0,0,B11/B7)
A12: Shipping & Fulfillment | C12: =IF(B7=0,0,B12/B7)
A13: Total COGS | B13: =SUM(B10:B12) | C13: =IF(B7=0,0,B13/B7)
A14: GROSS PROFIT | B14: =B7-B13 | C14: =IF(B7=0,0,B14/B7)
A16: OPERATING EXPENSES
A17: Supplies & Materials | C17: =IF(B7=0,0,B17/B7)
A18: Marketing & Advertising | C18: =IF(B7=0,0,B18/B7)
A19: Software & Subscriptions | C19: =IF(B7=0,0,B19/B7)
A20: Travel & Transportation | C20: =IF(B7=0,0,B20/B7)
A21: Meals & Entertainment | C21: =IF(B7=0,0,B21/B7)
A22: Office Expenses | C22: =IF(B7=0,0,B22/B7)
A23: Professional Services | C23: =IF(B7=0,0,B23/B7)
A24: Insurance | C24: =IF(B7=0,0,B24/B7)
A25: Utilities & Rent | C25: =IF(B7=0,0,B25/B7)
A26: Payroll & Contractors | C26: =IF(B7=0,0,B26/B7)
A27: Depreciation | C27: =IF(B7=0,0,B27/B7)
A28: Other Expenses | C28: =IF(B7=0,0,B28/B7)
A29: Total Operating Expenses | B29: =SUM(B17:B28) | C29: =IF(B7=0,0,B29/B7)
A31: NET PROFIT / (LOSS) | B31: =B14-B29 | C31: =IF(B7=0,0,B31/B7)

Sheet December
A1: Profit & Loss Statement - December 2026
A3: REVENUE | B3: Amount | C3: % of Revenue
A4: Product Sales | C4: =IF(B7=0,0,B4/B7)
A5: Service Revenue | C5: =IF(B7=0,0,B5/B7)
A6: Other Revenue | C6: =IF(B7=0,0,B6/B7)
A7: Total Revenue | B7: =SUM(B4:B6) | C7: 1
A9: COST OF GOODS SOLD
A10: Materials & Supplies | C10: =IF(B7=0,0,B10/B7)
A11: Direct Labor | C11: =IF(B7=0,0,B11/B7)
A12: Shipping & Fulfillment | C12: =IF(B7=0,0,B12/B7)
A13: Total COGS | B13: =SUM(B10:B12) | C13: =IF(B7=0,0,B13/B7)
A14: GROSS PROFIT | B14: =B7-B13 | C14: =IF(B7=0,0,B14/B7)
A16: OPERATING EXPENSES
A17: Supplies & Materials | C17: =IF(B7=0,0,B17/B7)
A18: Marketing & Advertising | C18: =IF(B7=0,0,B18/B7)
A19: Software & Subscriptions | C19: =IF(B7=0,0,B19/B7)
A20: Travel & Transportation | C20: =IF(B7=0,0,B20/B7)
A21: Meals & Entertainment | C21: =IF(B7=0,0,B21/B7)
A22: Office Expenses | C22: =IF(B7=0,0,B22/B7)
A23: Professional Services | C23: =IF(B7=0,0,B23/B7)
A24: Insurance | C24: =IF(B7=0,0,B24/B7)
A25: Utilities & Rent | C25: =IF(B7=0,0,B25/B7)
A26: Payroll & Contractors | C26: =IF(B7=0,0,B26/B7)
A27: Depreciation | C27: =IF(B7=0,0,B27/B7)
A28: Other Expenses | C28: =IF(B7=0,0,B28/B7)
A29: Total Operating Expenses | B29: =SUM(B17:B28) | C29: =IF(B7=0,0,B29/B7)
A31: NET PROFIT / (LOSS) | B31: =B14-B29 | C31: =IF(B7=0,0,B31/B7)
