Workbook

Sheet How to Use
A1: Wedding Planner Bundle — How to Use
A2: Your Complete Guide to Every Tab | Tips & Best Practices
B4: General Tips
B5: • Save a backup copy before making major changes.
B6: • Use Ctrl+S frequently — spreadsheets do not auto-save.
B7: • Do NOT delete formula cells (they are in the TOTAL/summary rows).
B8: • Dropdown menus appear when you click a cell — look for the small arrow.
B9: • Colored cells indicate formulas or conditional formatting — avoid overwriting.
B10: • Print individual tabs by right-clicking the tab → Print.
B11: • This workbook is fully customizable — change colors, add rows, adjust as needed!
B13: Wedding Dashboard | E13: Budget Tracker
B14: • This is your command center — start here every time you open the file. | E14: • All 23 common wedding categories are pre-loaded — add more rows as needed.
B15: • Enter your wedding date in cell C6; the countdown formula updates automatically. | E15: • Enter Estimated Cost first, then update Actual Cost as you book vendors.
B16: • The budget summary pulls totals from the Budget Tracker tab via formulas. | E16: • The Deposit Paid and Balance Due columns help you track payment schedules.
B17: • The RSVP summary also links to the Guest List tab for real-time counts. | E17: • Mark 'Yes' in the Paid In Full column when a vendor is fully settled.
B18: • Use the Key Contacts section to keep your most important numbers handy. | E18: • The pie chart auto-updates to show your budget breakdown visually.
B19: • Review the countdown checklist to stay on track with planning milestones. | E19: • Totals at the bottom auto-calculate — never manually change the TOTAL row.
B21: Guest List & RSVPs | E21: Vendor Tracker
B22: • Pre-formatted for 150 guests — insert rows above the totals to add more. | E22: • 20 vendor categories are pre-filled — customize names and details.
B23: • Use the Side dropdown (Bride/Groom/Both) to balance your guest list. | E23: • Store ALL vendor contact info here for easy reference on the wedding day.
B24: • Track Plus Ones separately so catering counts are accurate. | E24: • Track contracts, deposits, and balances to avoid missed payments.
B25: • Update RSVP Status as responses arrive (Invited → Attending/Declined/Pending). | E25: • Balance Due auto-calculates as (Total Cost − Deposit Amount).
B26: • The auto-count totals at the bottom give you instant RSVP summaries. | E26: • Use the Notes column for special arrangements or package details.
B27: • Mark Thank You Sent to keep track of your gratitude notes.
B28: Timeline / Checklist | E28: Seating Chart
B29: • Organized from 12 months out to Wedding Day in logical timeframes. | E29: • Pre-set for 20 tables of 8 guests each (160 seats).
B30: • Each task has Priority (High/Medium/Low) and Status tracking. | E30: • Use Table Name/Theme for creative table identifiers.
B31: • Assign tasks to specific people (Bride, Groom, MOH, Best Man, etc.). | E31: • Enter guest names from your Guest List to cross-reference table assignments.
B32: • Status conditional formatting: Green=Done, Gold=In Progress, Mauve=Not Started. | E32: • Note dietary restrictions and special needs for catering and venue staff.
B33: • Add your own tasks as needed — keep the Timeframe column consistent. | E33: • Update the Table # column on the Guest List tab to match.
B35: Day-Of Timeline | E35: Gift & Thank You Tracker
B36: • A minute-by-minute schedule from 8 AM to 11 PM. | E36: • Log each gift as it arrives — don't rely on memory!
B37: • Assign a Person Responsible for each event so everyone knows their role. | E37: • Estimated Value helps with insurance and registry tracking.
B38: • Print copies for your coordinator, DJ, photographer, and bridal party. | E38: • Mark Thank You Written and Date Sent to ensure no one is overlooked.
B39: • Adjust times to match your ceremony and reception schedule. | E39: • Etiquette tip: send thank-you notes within 2-3 months of receiving a gift.
B40: • Use Status column day-of to mark events as they happen. | E40: • Use Notes for personal details to mention in your thank-you card.
B44: Congratulations on your engagement! Wishing you a beautiful wedding day.

Sheet Wedding Dashboard
A1: Wedding Dashboard
A2: Your Wedding At A Glance | Key Metrics & Countdown
B4: Wedding Date & Countdown | E4: RSVP Summary | H4: Quick To-Do Checklist
B5: Wedding Date: | C5: 06/20/2026 | E5: Total Invited: | F5: =COUNTA('Guest List & RSVPs'!B5:B154) | H5: Task | I5: Priority
B6: Days Until Wedding: | C6: =IF(C4="","",C4-TODAY()) | E6: Attending: | F6: =COUNTIF('Guest List & RSVPs'!K5:K154,"Attending") | H6: Book venue | I6: High
B7: Weeks Until Wedding: | C7: =IF(C4="","",INT((C4-TODAY())/7)) | E7: Declined: | F7: =COUNTIF('Guest List & RSVPs'!K5:K154,"Declined") | H7: Hire photographer | I7: High
E8: Pending: | F8: =COUNTIF('Guest List & RSVPs'!K5:K154,"Pending") | H8: Send save-the-dates | I8: High
B9: Budget Summary | H9: Choose wedding party | I9: Medium
B10: Total Budget (Estimated): | C10: ='Budget Tracker'!C27 | E10: Vendor Payment Status | H10: Book caterer | I10: High
B11: Total Spent (Actual): | C11: ='Budget Tracker'!D27 | E11: Contracts Signed: | F11: =COUNTIF('Vendor Tracker'!H5:H24,"Yes") | H11: Order invitations | I11: Medium
B12: Remaining: | C12: ='Budget Tracker'!C27-'Budget Tracker'!D27 | E12: Deposits Paid: | F12: =COUNTIF('Vendor Tracker'!J5:J24,"Yes") | H12: Schedule tastings | I12: Medium
B13: % Used: | C13: =IF('Budget Tracker'!C27=0,0,'Budget Tracker'!D27/'Budget Tracker'!C27) | E13: Fully Paid: | F13: =COUNTIF('Vendor Tracker'!N5:N24,"Paid") | H13: Plan honeymoon | I13: Medium
E14: Total Vendor Cost: | F14: =SUM('Vendor Tracker'!K5:K24) | H14: Buy wedding rings | I14: High
B15: Key Contacts | H15: Final dress fitting | I15: High
A16: Role | B16: Role | C16: Name | D16: Phone | E16: Email | F16: Notes | H16: Confirm all vendors | I16: High
B17: Wedding Coordinator | H17: Write vows | I17: Medium
B18: Venue Contact
B19: Caterer
B20: Photographer
B21: DJ / Band
B22: Florist
B23: Officiant
B24: Hair & Makeup

Sheet Budget Tracker
A1: Wedding Budget Tracker
A2: Track Every Dollar | Estimated vs. Actual | Auto-Calculated Totals
A3: Category | B3: Estimated Cost | C3: Actual Cost | D3: Deposit Paid | E3: Balance Due | F3: Paid In Full | G3: Notes
A4: Venue | E4: =IF(C4="","",C4-D4)
A5: Catering | E5: =IF(C5="","",C5-D5)
A6: Photography | E6: =IF(C6="","",C6-D6)
A7: Videography | E7: =IF(C7="","",C7-D7)
A8: Flowers / Florist | E8: =IF(C8="","",C8-D8)
A9: Music / DJ | E9: =IF(C9="","",C9-D9)
A10: Wedding Dress | E10: =IF(C10="","",C10-D10)
A11: Groom's Attire | E11: =IF(C11="","",C11-D11)
A12: Bridesmaids | E12: =IF(C12="","",C12-D12)
A13: Groomsmen | E13: =IF(C13="","",C13-D13)
A14: Hair & Makeup | E14: =IF(C14="","",C14-D14)
A15: Invitations / Stationery | E15: =IF(C15="","",C15-D15)
... A26: Miscellaneous | E26: =IF(C26="","",C26-D26)
A27: TOTAL | B27: =SUM(B4:B26) | C27: =SUM(C4:C26) | D27: =SUM(D4:D26) | E27: =SUM(E4:E26)

Sheet Guest List & RSVPs
A1: Guest List & RSVPs
A2: Track Every Guest | RSVPs | Dietary Needs | Thank You Notes
A3: Guest Name | B3: Email | C3: Phone | D3: Address | E3: Side | F3: Relationship | G3: Plus One | H3: Plus One Name | I3: Dietary Needs | J3: RSVP Status | K3: Table # | L3: Gift Received | M3: Thank You Sent | N3: Notes
A155: RSVP SUMMARY
A156: Total Invited: | B156: =COUNTA(A4:A153)
A157: Attending: | B157: =COUNTIF(J4:J153,"Attending")
A158: Declined: | B158: =COUNTIF(J4:J153,"Declined")
A159: Pending: | B159: =COUNTIF(J4:J153,"Pending")
A160: Plus Ones: | B160: =COUNTIF(G4:G153,"Yes")
A161: Thank Yous Sent: | B161: =COUNTIF(M4:M153,"Yes")

Sheet Vendor Tracker
A1: Vendor Tracker
A2: Contacts | Contracts | Payments | All Vendor Details
A3: Vendor Category | B3: Vendor Name | C3: Contact Name | D3: Phone | E3: Email | F3: Website | G3: Contract Signed | H3: Deposit Amount | I3: Deposit Paid | J3: Total Cost | K3: Payment Due Date | L3: Balance Due | M3: Payment Status | N3: Notes
A4: Venue | L4: =IF(J4="","",J4-H4)
A5: Caterer | L5: =IF(J5="","",J5-H5)
A6: Photographer | L6: =IF(J6="","",J6-H6)
A7: Videographer | L7: =IF(J7="","",J7-H7)
A8: Florist | L8: =IF(J8="","",J8-H8)
A9: DJ / Band | L9: =IF(J9="","",J9-H9)
A10: Wedding Planner | L10: =IF(J10="","",J10-H10)
A11: Officiant | L11: =IF(J11="","",J11-H11)
A12: Baker (Cake) | L12: =IF(J12="","",J12-H12)
A13: Hair Stylist | L13: =IF(J13="","",J13-H13)
A14: Makeup Artist | L14: =IF(J14="","",J14-H14)
A15: Dress / Bridal Shop | L15: =IF(J15="","",J15-H15)
... A23: Hotel / Accommodations | L23: =IF(J23="","",J23-H23)
A24: TOTALS | H24: =SUM(H4:H23) | J24: =SUM(J4:J23) | L24: =SUM(L4:L23)

Sheet Timeline & Checklist
A1: Wedding Timeline & Master Checklist
A2: 12 Months to Wedding Day | Every Task Organized by Timeframe
A3: Timeframe | B3: Task | C3: Category | D3: Assigned To | E3: Due Date | F3: Status | G3: Priority | H3: Notes
A4: 12 Months Before | B4: Set budget | C4: Budget | D4: Couple
A5: 12 Months Before | B5: Choose wedding date | C5: Planning | D5: Couple
A6: 12 Months Before | B6: Book venue | C6: Venue | D6: Couple
A7: 12 Months Before | B7: Hire wedding planner | C7: Planning | D7: Couple
A8: 12 Months Before | B8: Start guest list draft | C8: Guest List | D8: Couple
A9: 12 Months Before | B9: Research photographers | C9: Photography | D9: Bride
A10: 12 Months Before | B10: Begin dress shopping | C10: Attire | D10: Bride
A11: 12 Months Before | B11: Book officiant | C11: Ceremony | D11: Couple
A12: 9 Months Before | B12: Book photographer | C12: Photography | D12: Couple
A13: 9 Months Before | B13: Book videographer | C13: Photography | D13: Couple
A14: 9 Months Before | B14: Book caterer / tasting | C14: Catering | D14: Couple
A15: 9 Months Before | B15: Choose wedding party | C15: Planning | D15: Couple
... A68: Wedding Day | B68: Send-off / exit | C68: Reception | D68: All

Sheet Seating Chart
A1: Seating Chart
A2: Table Assignments | 20 Tables x 8 Guests | Dietary & Special Needs
A3: Table # | B3: Table Name / Theme | C3: Capacity | D3: Guest 1 | E3: Guest 2 | F3: Guest 3 | G3: Guest 4 | H3: Guest 5 | I3: Guest 6 | J3: Guest 7 | K3: Guest 8 | L3: Dietary Notes | M3: Special Needs
A4: 1 | C4: 8
A5: 2 | C5: 8
A6: 3 | C6: 8
A7: 4 | C7: 8
A8: 5 | C8: 8
A9: 6 | C9: 8
A10: 7 | C10: 8
A11: 8 | C11: 8
A12: 9 | C12: 8
A13: 10 | C13: 8
A14: 11 | C14: 8
A15: 12 | C15: 8
... A23: 20 | C23: 8

Sheet Day-Of Timeline
A1: Day-Of Timeline
A2: Minute-by-Minute Wedding Day Schedule | 8 AM to 11 PM
A3: Time | B3: Event / Activity | C3: Location | D3: Person Responsible | E3: Notes / Details | F3: Status
A4: 8:00 AM | B4: Bridal party hair & makeup begins | C4: Bridal Suite | D4: Hair/Makeup Team | E4: Allow 3-4 hours for full party
A5: 8:30 AM | B5: Breakfast for bridal party | C5: Bridal Suite | D5: MOH / Coordinator | E5: Light, non-messy foods
A6: 9:00 AM | B6: Groom & groomsmen breakfast | C6: Groom's Room | D6: Best Man | E6: Keep it casual and fun
A7: 10:00 AM | B7: Photographer arrives | C7: Bridal Suite | D7: Photographer | E7: Detail shots: dress, rings, shoes, invites
A8: 10:30 AM | B8: Videographer arrives | C8: Venue | D8: Videographer | E8: Establish shots of venue
A9: 11:00 AM | B9: Bride gets dressed | C9: Bridal Suite | D9: MOH / Mother | E9: Schedule 30 min for photos
A10: 11:30 AM | B10: Groom gets dressed | C10: Groom's Room | D10: Best Man | E10: Boutonniere pinning
A11: 12:00 PM | B11: First Look (optional) | C11: Garden / Venue | D11: Photographer | E11: Private moment, 15-20 min
A12: 12:30 PM | B12: Wedding party photos | C12: Venue Grounds | D12: Photographer | E12: Group and individual shots
A13: 1:00 PM | B13: Family formal photos | C13: Venue | D13: Photographer | E13: Pre-arrange family groupings
A14: 1:30 PM | B14: Bridal party hidden / guests arrive | C14: Ceremony Area | D14: Coordinator | E14: Ushers seat guests
A15: 2:00 PM | B15: Musicians / DJ begin prelude | C15: Ceremony Area | D15: DJ / Musicians | E15: 30 min of ambient music
... A45: 11:00 PM | B45: Venue cleanup / breakdown | C45: Venue | D45: Coordinator / Rentals | E45: Collect personal items & gifts

Sheet Gift & Thank You Tracker
A1: Gift & Thank You Tracker
A2: Log Every Gift | Track Thank You Notes | Never Miss a Thank You
A3: Guest Name | B3: Gift Description | C3: Estimated Value | D3: Date Received | E3: Thank You Written | F3: Date Sent | G3: Notes
A105: GIFT SUMMARY
A106: Total Gifts Received: | B106: =COUNTA(A4:A103)
A107: Total Estimated Value: | B107: =SUM(C4:C103)
A108: Thank Yous Sent: | B108: =COUNTIF(E4:E103,"Yes")
A109: Thank Yous Remaining: | B109: =COUNTIF(E4:E103,"No")
